gsmo/__init__.py
gsmo/cli.py
gsmo/conf.py
gsmo/config.py
gsmo/control.py
gsmo/entrypoint.py
gsmo/err.py
gsmo/git.py
gsmo/gsmo.py
gsmo/lock.py
gsmo/modules.py
gsmo/mount.py
gsmo/papermill.py
gsmo/version.py
gsmo/util/__init__.py
gsmo/util/unix_id.py
gsmo-0.1.5.dist-info/METADATA
gsmo-0.1.5.dist-info/WHEEL
gsmo-0.1.5.dist-info/entry_points.txt
gsmo-0.1.5.dist-info/top_level.txt
gsmo-0.1.5.dist-info/RECORD
