Metadata-Version: 2.1
Name: gsmo
Version: 0.1.5
Summary: Commonsense Git, Docker, and Jupyter integrations.
Home-page: https://github.com/runsascoded/gsmo
Author: Ryan Williams
Author-email: ryan@runsascoded.com
License: UNKNOWN
Platform: UNKNOWN
Classifier: Programming Language :: Python :: 3
Classifier: Operating System :: OS Independent
Requires-Python: >=3.8
Requires-Dist: papermill
Requires-Dist: pyyaml
Requires-Dist: utz[setup] (>=0.3.15)
Provides-Extra: test
Requires-Dist: GitPython ; extra == 'test'
Requires-Dist: pytest (==6.0.1) ; extra == 'test'
